{
    "SN2007il_2007-09-12_other_1.ascii": {
        "Type": "SN II",
        "Redshift": "0.021",
        "Obs. Date": "2007-09-12",
        "Program": "",
        "Contributor": "",
        "Bibcode": "",
        "Instrument": "Other - Other",
        "Observer": "Unknown",
        "Reducer": "Unknown",
        "Reduction Status": "final",
        "Last Modified": "2016-08-31",
        "Modified By": "admin-UploadSet"
    },
    "SN2007il_2007-09-15_other_2.ascii": {
        "Type": "SN II",
        "Redshift": "0.021",
        "Obs. Date": "2007-09-15",
        "Program": "",
        "Contributor": "",
        "Bibcode": "",
        "Instrument": "Other - Other",
        "Observer": "Unknown",
        "Reducer": "Unknown",
        "Reduction Status": "final",
        "Last Modified": "2016-08-31",
        "Modified By": "admin-UploadSet"
    }
}