{
    "10iuf_20100607_WHT_v1.ascii": {
        "Type": "SN Ia", 
        "Redshift": "0.1586", 
        "Obs. Date": "2010-06-07", 
        "Program": "PTF", 
        "Contributor": "Silverman et al. 2013", 
        "Bibcode": "2013ApJS..207....3S", 
        "Instrument": "WHT-4.2m - ISIS", 
        "Observer": "QUB", 
        "Reduction Status": "final", 
        "Last Modified": "2011-11-23", 
        "Modified By": "upload-marshalspec"
    }, 
    "10iuf_20100612_Keck1_v1.ascii": {
        "Type": "SN Ia", 
        "Redshift": "0.1586", 
        "Obs. Date": "2010-06-12", 
        "Program": "PTF", 
        "Contributor": "Silverman et al. 2013", 
        "Bibcode": "2013ApJS..207....3S", 
        "Instrument": "Keck1 - LRIS", 
        "Observer": "Filippenko, Silverman, Cenko", 
        "Reduction Status": "final", 
        "Last Modified": "2011-11-23", 
        "Modified By": "upload-marshalspec"
    }, 
    "10iuf_20100707_Keck1_v2.ascii": {
        "Type": "SN Ia", 
        "Redshift": "0.1586", 
        "Obs. Date": "2010-07-07", 
        "Program": "PTF", 
        "Contributor": "Silverman et al. 2013", 
        "Bibcode": "2013ApJS..207....3S", 
        "Instrument": "Keck1 - LRIS", 
        "Observer": "Cenko, Perley, Cucchiara, Bloom", 
        "Reduction Status": "final", 
        "Last Modified": "2011-11-23", 
        "Modified By": "upload-marshalspec"
    }, 
    "10iuf_20100801_WHT_v1.ascii": {
        "Type": "SN Ia", 
        "Redshift": "0.1586", 
        "Obs. Date": "2010-08-01", 
        "Program": "PTF", 
        "Contributor": "Silverman et al. 2013", 
        "Bibcode": "2013ApJS..207....3S", 
        "Instrument": "WHT-4.2m - ISIS", 
        "Observer": "Sullivan", 
        "Reduction Status": "final", 
        "Last Modified": "2011-11-23", 
        "Modified By": "upload-marshalspec"
    }, 
    "10iuf_20100808_P200_v1.ascii": {
        "Type": "SN Ia", 
        "Redshift": "0.1586", 
        "Obs. Date": "2010-08-08", 
        "Program": "PTF", 
        "Contributor": "Silverman et al. 2013", 
        "Bibcode": "2013ApJS..207....3S", 
        "Instrument": "P200 - DBSP", 
        "Observer": "Arcavi", 
        "Reduction Status": "final", 
        "Last Modified": "2011-11-23", 
        "Modified By": "upload-marshalspec"
    }, 
    "10iuf_20101012_Keck2_v1.ascii": {
        "Type": "SN Ia", 
        "Redshift": "0.1586", 
        "Obs. Date": "2010-10-12", 
        "Program": "PTF", 
        "Contributor": "Silverman et al. 2013", 
        "Bibcode": "2013ApJS..207....3S", 
        "Instrument": "Keck2 - DEIMOS", 
        "Observer": "Silverman, Cenko, Filippenko", 
        "Reduction Status": "final", 
        "Last Modified": "2011-11-23", 
        "Modified By": "upload-marshalspec"
    }
}