{
    "snonly_05D2ci_799_Balland_etal_09.dat": {
        "Type": "SN Ia",
        "Redshift": "0.63",
        "Obs. Date": "2005-03-06",
        "Program": "SNLS",
        "Contributor": "Balland et al. 2009",
        "Bibcode": "2009A&A...507...85B",
        "Instrument": "VLT-UT1 - FORS1",
        "Observer": "Unknown",
        "Reducer": "Unknown",
        "Reduction Status": "final",
        "Last Modified": "2013-04-02",
        "Modified By": "ilanm-UploadSet"
    },
    "snonly_05D2ci_795_Balland_etal_09.dat": {
        "Type": "SN Ia",
        "Redshift": "0.63",
        "Obs. Date": "2005-03-07",
        "Program": "SNLS",
        "Contributor": "Balland et al. 2009",
        "Bibcode": "2009A&A...507...85B",
        "Instrument": "VLT-UT1 - FORS1",
        "Observer": "Unknown",
        "Reducer": "Unknown",
        "Reduction Status": "final",
        "Last Modified": "2013-04-02",
        "Modified By": "ilanm-UploadSet"
    },
    "snonly_05D2ci_796_Balland_etal_09.dat": {
        "Type": "SN Ia",
        "Redshift": "0.63",
        "Obs. Date": "2005-03-10",
        "Program": "SNLS",
        "Contributor": "Balland et al. 2009",
        "Bibcode": "2009A&A...507...85B",
        "Instrument": "VLT-UT1 - FORS1",
        "Observer": "Unknown",
        "Reducer": "Unknown",
        "Reduction Status": "final",
        "Last Modified": "2013-04-02",
        "Modified By": "ilanm-UploadSet"
    },
    "Private Spectra": "0"
}