{
    "2014G_20140114_P122_BC_300tr_p.dat": {
        "Type": "SN IIL",
        "Redshift": "0.0039",
        "Obs. Date": "2014-01-14",
        "Program": "",
        "Contributor": "Terreran et al. 2016",
        "Bibcode": "2016arXiv160506116T",
        "Instrument": "Galileo - B&C-Asi-1.22m",
        "Observer": "Ochner Dalla Bonta",
        "Reducer": "Terreran",
        "Reduction Status": "final",
        "Last Modified": "2016-08-10",
        "Modified By": "ilanm"
    },
    "2014G_20140115_P122_BC_300tr_p.dat": {
        "Type": "SN IIL",
        "Redshift": "0.0039",
        "Obs. Date": "2014-01-15",
        "Program": "",
        "Contributor": "Terreran et al. 2016",
        "Bibcode": "2016arXiv160506116T",
        "Instrument": "Galileo - B&C-Asi-1.22m",
        "Observer": "Ochner Dalla Bonta",
        "Reducer": "Terreran",
        "Reduction Status": "final",
        "Last Modified": "2016-08-10",
        "Modified By": "ilanm"
    },
    "2014G_20140121_P122_BC_300tr_p.dat": {
        "Type": "SN IIL",
        "Redshift": "0.0039",
        "Obs. Date": "2014-01-21",
        "Program": "",
        "Contributor": "Terreran et al. 2016",
        "Bibcode": "2016arXiv160506116T",
        "Instrument": "Galileo - B&C-Asi-1.22m",
        "Observer": "Ochner",
        "Reducer": "Terreran",
        "Reduction Status": "final",
        "Last Modified": "2016-08-10",
        "Modified By": "ilanm"
    },
    "2014G_20140125_AFOSC_gr4+vph6_p.dat": {
        "Type": "SN IIL",
        "Redshift": "0.0039",
        "Obs. Date": "2014-01-25",
        "Program": "",
        "Contributor": "Terreran et al. 2016",
        "Bibcode": "2016arXiv160506116T",
        "Instrument": "Ekar - AFOSC",
        "Observer": "Tomasella",
        "Reducer": "Terreran",
        "Reduction Status": "final",
        "Last Modified": "2016-08-10",
        "Modified By": "ilanm"
    },
    "2014G_20140129_P122_BC_300tr_p.dat": {
        "Type": "SN IIL",
        "Redshift": "0.0039",
        "Obs. Date": "2014-01-29",
        "Program": "",
        "Contributor": "Terreran et al. 2016",
        "Bibcode": "2016arXiv160506116T",
        "Instrument": "Galileo - B&C-Asi-1.22m",
        "Observer": "Ochner",
        "Reducer": "Terreran",
        "Reduction Status": "final",
        "Last Modified": "2016-08-10",
        "Modified By": "ilanm"
    },
    "2014G_20140206_P122_BC_300tr_p.dat": {
        "Type": "SN IIL",
        "Redshift": "0.0039",
        "Obs. Date": "2014-02-06",
        "Program": "",
        "Contributor": "Terreran et al. 2016",
        "Bibcode": "2016arXiv160506116T",
        "Instrument": "Galileo - B&C-Asi-1.22m",
        "Observer": "Ochner",
        "Reducer": "Terreran",
        "Reduction Status": "final",
        "Last Modified": "2016-08-10",
        "Modified By": "ilanm"
    },
    "2014G_20140217_P122_BC_300tr_p.dat": {
        "Type": "SN IIL",
        "Redshift": "0.0039",
        "Obs. Date": "2014-02-17",
        "Program": "",
        "Contributor": "Terreran et al. 2016",
        "Bibcode": "2016arXiv160506116T",
        "Instrument": "Galileo - B&C-Asi-1.22m",
        "Observer": "Ochner",
        "Reducer": "Terreran",
        "Reduction Status": "final",
        "Last Modified": "2016-08-10",
        "Modified By": "ilanm"
    },
    "2014G_20140219_Dolores_B+R_p.dat": {
        "Type": "SN IIL",
        "Redshift": "0.0039",
        "Obs. Date": "2014-02-19",
        "Program": "",
        "Contributor": "Terreran et al. 2016",
        "Bibcode": "2016arXiv160506116T",
        "Instrument": "TNG - DOLORES",
        "Observer": "Unknown",
        "Reducer": "Terreran",
        "Reduction Status": "final",
        "Last Modified": "2016-08-10",
        "Modified By": "ilanm"
    },
    "2014G_20140226_Dolores_B+R_p.dat": {
        "Type": "SN IIL",
        "Redshift": "0.0039",
        "Obs. Date": "2014-02-26",
        "Program": "",
        "Contributor": "Terreran et al. 2016",
        "Bibcode": "2016arXiv160506116T",
        "Instrument": "TNG - DOLORES",
        "Observer": "Unknown",
        "Reducer": "Terreran",
        "Reduction Status": "final",
        "Last Modified": "2016-08-10",
        "Modified By": "ilanm"
    },
    "2014G_20140306_P122_BC_300tr_p.dat": {
        "Type": "SN IIL",
        "Redshift": "0.0039",
        "Obs. Date": "2014-03-06",
        "Program": "",
        "Contributor": "Terreran et al. 2016",
        "Bibcode": "2016arXiv160506116T",
        "Instrument": "Galileo - B&C-Asi-1.22m",
        "Observer": "Ochner",
        "Reducer": "Terreran",
        "Reduction Status": "final",
        "Last Modified": "2016-08-10",
        "Modified By": "ilanm"
    },
    "2014G_20140310_AFOSC_gr4_p.dat": {
        "Type": "SN IIL",
        "Redshift": "0.0039",
        "Obs. Date": "2014-03-10",
        "Program": "",
        "Contributor": "Terreran et al. 2016",
        "Bibcode": "2016arXiv160506116T",
        "Instrument": "Ekar - AFOSC",
        "Observer": "Tomasella",
        "Reducer": "Terreran",
        "Reduction Status": "final",
        "Last Modified": "2016-08-10",
        "Modified By": "ilanm"
    },
    "2014G_20140317_P122_BC_300tr_p.dat": {
        "Type": "SN IIL",
        "Redshift": "0.0039",
        "Obs. Date": "2014-03-17",
        "Program": "",
        "Contributor": "Terreran et al. 2016",
        "Bibcode": "2016arXiv160506116T",
        "Instrument": "Galileo - B&C-Asi-1.22m",
        "Observer": "Ochner",
        "Reducer": "Terreran",
        "Reduction Status": "final",
        "Last Modified": "2016-08-10",
        "Modified By": "ilanm"
    },
    "2014G_20140330_AFOSC_GR04+VPH6_p.dat": {
        "Type": "SN IIL",
        "Redshift": "0.0039",
        "Obs. Date": "2014-03-30",
        "Program": "",
        "Contributor": "Terreran et al. 2016",
        "Bibcode": "2016arXiv160506116T",
        "Instrument": "Ekar - AFOSC",
        "Observer": "Terreran Tomasella",
        "Reducer": "Terreran",
        "Reduction Status": "final",
        "Last Modified": "2016-08-10",
        "Modified By": "ilanm"
    },
    "2014G_20140407_AFOSC_GR04+VPH6_p.dat": {
        "Type": "SN IIL",
        "Redshift": "0.0039",
        "Obs. Date": "2014-04-07",
        "Program": "",
        "Contributor": "Terreran et al. 2016",
        "Bibcode": "2016arXiv160506116T",
        "Instrument": "Ekar - AFOSC",
        "Observer": "Ochner Tartaglia Tomasella",
        "Reducer": "Terreran",
        "Reduction Status": "final",
        "Last Modified": "2016-08-10",
        "Modified By": "ilanm"
    },
    "2014G_20140425_ALFOSC_gm4_p.dat": {
        "Type": "SN IIL",
        "Redshift": "0.0039",
        "Obs. Date": "2014-04-25",
        "Program": "",
        "Contributor": "Terreran et al. 2016",
        "Bibcode": "2016arXiv160506116T",
        "Instrument": "Ekar - AFOSC",
        "Observer": "Axl Rose",
        "Reducer": "Terreran",
        "Reduction Status": "final",
        "Last Modified": "2016-08-10",
        "Modified By": "ilanm"
    },
    "2014G_20140511_Dolores_B_p.dat": {
        "Type": "SN IIL",
        "Redshift": "0.0039",
        "Obs. Date": "2014-05-11",
        "Program": "",
        "Contributor": "Terreran et al. 2016",
        "Bibcode": "2016arXiv160506116T",
        "Instrument": "TNG - DOLORES",
        "Observer": "Unknown",
        "Reducer": "Terreran",
        "Reduction Status": "final",
        "Last Modified": "2016-08-10",
        "Modified By": "ilanm"
    },
    "2014G_20140529_TNG_LRS_p.dat": {
        "Type": "SN IIL",
        "Redshift": "0.0039",
        "Obs. Date": "2014-05-29",
        "Program": "",
        "Contributor": "Terreran et al. 2016",
        "Bibcode": "2016arXiv160506116T",
        "Instrument": "TNG - DOLORES",
        "Observer": "Unknown",
        "Reducer": "Terreran",
        "Reduction Status": "final",
        "Last Modified": "2016-08-10",
        "Modified By": "ilanm"
    },
    "2014G_20140718_Dolores_R_p.dat": {
        "Type": "SN IIL",
        "Redshift": "0.0039",
        "Obs. Date": "2014-07-18",
        "Program": "",
        "Contributor": "Terreran et al. 2016",
        "Bibcode": "2016arXiv160506116T",
        "Instrument": "TNG - DOLORES",
        "Observer": "Unknown",
        "Reducer": "Terreran",
        "Reduction Status": "final",
        "Last Modified": "2016-08-10",
        "Modified By": "ilanm"
    },
    "2014G_20141220_GTC_OSIRIS_p.dat": {
        "Type": "SN IIL",
        "Redshift": "0.0039",
        "Obs. Date": "2014-12-20",
        "Program": "",
        "Contributor": "Terreran et al. 2016",
        "Bibcode": "2016arXiv160506116T",
        "Instrument": "GTC - OSIRIS",
        "Observer": "SA",
        "Reducer": "Terreran",
        "Reduction Status": "final",
        "Last Modified": "2016-08-10",
        "Modified By": "ilanm"
    }
}