{
    "sn2011ht_20111122_sn2011ht_apo112211.txt": {
        "Type": "SN IIn", 
        "Redshift": "0.0036", 
        "Obs. Date": "2011-11-22", 
        "Program": "", 
        "Contributor": "Humphreys et al. 2012", 
        "Bibcode": "2012ApJ...760...93H", 
        "Instrument": "APO 3.5m - DIS", 
        "Observer": "Unknown", 
        "Reduction Status": "final", 
        "Last Modified": "2013-08-08", 
        "Modified By": "stefana-UploadSet"
    }, 
    "sn2011ht_20111123_sn2011ht_blue11.23.txt": {
        "Type": "SN IIn", 
        "Redshift": "0.0036", 
        "Obs. Date": "2011-11-23", 
        "Program": "", 
        "Contributor": "Humphreys et al. 2012", 
        "Bibcode": "2012ApJ...760...93H", 
        "Instrument": "LBT - MODS1", 
        "Observer": "R. Stoll, K. Stanek", 
        "Reduction Status": "final", 
        "Last Modified": "2013-08-08", 
        "Modified By": "stefana-UploadSet"
    }, 
    "sn2011ht_20120103_sn2011ht_apo010212.txt": {
        "Type": "SN IIn", 
        "Redshift": "0.0036", 
        "Obs. Date": "2012-01-03", 
        "Program": "", 
        "Contributor": "Humphreys et al. 2012", 
        "Bibcode": "2012ApJ...760...93H", 
        "Instrument": "APO 3.5m - DIS", 
        "Observer": "Unknown", 
        "Reduction Status": "final", 
        "Last Modified": "2013-08-08", 
        "Modified By": "stefana-UploadSet"
    }, 
    "sn2011ht_20120123_sn2011ht_flux230112.txt": {
        "Type": "SN IIn", 
        "Redshift": "0.0036", 
        "Obs. Date": "2012-01-23", 
        "Program": "", 
        "Contributor": "Humphreys et al. 2012", 
        "Bibcode": "2012ApJ...760...93H", 
        "Instrument": "MMT - Hectospec", 
        "Observer": "M.A., K.W., P.B.", 
        "Reduction Status": "final", 
        "Last Modified": "2013-08-08", 
        "Modified By": "stefana-UploadSet"
    }, 
    "sn2011ht_20120123_sn2011ht_fluxSmoo230112.txt": {
        "Type": "SN IIn", 
        "Redshift": "0.0036", 
        "Obs. Date": "2012-01-23", 
        "Program": "", 
        "Contributor": "Humphreys et al. 2012", 
        "Bibcode": "2012ApJ...760...93H", 
        "Instrument": "MMT - Hectospec", 
        "Observer": "M.A., K.W., P.B.", 
        "Reduction Status": "final", 
        "Last Modified": "2013-08-08", 
        "Modified By": "stefana-UploadSet"
    }, 
    "sn2011ht_20120213_sn2011ht_flux130212.txt": {
        "Type": "SN IIn", 
        "Redshift": "0.0036", 
        "Obs. Date": "2012-02-13", 
        "Program": "", 
        "Contributor": "Humphreys et al. 2012", 
        "Bibcode": "2012ApJ...760...93H", 
        "Instrument": "MMT - Hectospec", 
        "Observer": "P.B., M.K.", 
        "Reduction Status": "final", 
        "Last Modified": "2013-08-08", 
        "Modified By": "stefana-UploadSet"
    }, 
    "sn2011ht_20120213_sn2011ht_fluxSmoo130212.txt": {
        "Type": "SN IIn", 
        "Redshift": "0.0036", 
        "Obs. Date": "2012-02-13", 
        "Program": "", 
        "Contributor": "Humphreys et al. 2012", 
        "Bibcode": "2012ApJ...760...93H", 
        "Instrument": "MMT - Hectospec", 
        "Observer": "P.B., M.K.", 
        "Reduction Status": "final", 
        "Last Modified": "2013-08-08", 
        "Modified By": "stefana-UploadSet"
    }, 
    "sn2011ht_20120228_sn2011ht_apo022212.txt": {
        "Type": "SN IIn", 
        "Redshift": "0.0036", 
        "Obs. Date": "2012-02-28", 
        "Program": "", 
        "Contributor": "Humphreys et al. 2012", 
        "Bibcode": "2012ApJ...760...93H", 
        "Instrument": "APO 3.5m - DIS", 
        "Observer": "Unknown", 
        "Reduction Status": "final", 
        "Last Modified": "2013-08-08", 
        "Modified By": "stefana-UploadSet"
    }, 
    "sn2011ht_20120229_sn2011ht_apo011912.txt": {
        "Type": "SN IIn", 
        "Redshift": "0.0036", 
        "Obs. Date": "2012-02-29", 
        "Program": "", 
        "Contributor": "Humphreys et al. 2012", 
        "Bibcode": "2012ApJ...760...93H", 
        "Instrument": "APO 3.5m - DIS", 
        "Observer": "Unknown", 
        "Reduction Status": "final", 
        "Last Modified": "2013-08-08", 
        "Modified By": "stefana-UploadSet"
    }, 
    "sn2011ht_20120302_sn2011ht_apo022812.txt": {
        "Type": "SN IIn", 
        "Redshift": "0.0036", 
        "Obs. Date": "2012-03-02", 
        "Program": "", 
        "Contributor": "Humphreys et al. 2012", 
        "Bibcode": "2012ApJ...760...93H", 
        "Instrument": "APO 3.5m - DIS", 
        "Observer": "Unknown", 
        "Reduction Status": "final", 
        "Last Modified": "2013-08-08", 
        "Modified By": "stefana-UploadSet"
    }, 
    "sn2011ht_20120416_sn2011ht_blue1226.txt": {
        "Type": "SN IIn", 
        "Redshift": "0.0036", 
        "Obs. Date": "2012-04-16", 
        "Program": "", 
        "Contributor": "Humphreys et al. 2012", 
        "Bibcode": "2012ApJ...760...93H", 
        "Instrument": "LBT - MODS1", 
        "Observer": "R. Green, W. Bian, F. Bian", 
        "Reduction Status": "final", 
        "Last Modified": "2013-08-08", 
        "Modified By": "stefana-UploadSet"
    }, 
    "sn2011ht_20120416_sn2011ht_blue1228.txt": {
        "Type": "SN IIn", 
        "Redshift": "0.0036", 
        "Obs. Date": "2012-04-16", 
        "Program": "", 
        "Contributor": "Humphreys et al. 2012", 
        "Bibcode": "2012ApJ...760...93H", 
        "Instrument": "LBT - MODS1", 
        "Observer": "B. Shappee, E. Ryan, R. Green, W. Bian", 
        "Reduction Status": "final", 
        "Last Modified": "2013-08-08", 
        "Modified By": "stefana-UploadSet"
    }, 
    "sn2011ht_20120416_sn2011ht_red11.17.txt": {
        "Type": "SN IIn", 
        "Redshift": "0.0036", 
        "Obs. Date": "2012-04-16", 
        "Program": "", 
        "Contributor": "Humphreys et al. 2012", 
        "Bibcode": "2012ApJ...760...93H", 
        "Instrument": "LBT - MODS1", 
        "Observer": "R. Stoll, K. Stanek", 
        "Reduction Status": "final", 
        "Last Modified": "2013-08-08", 
        "Modified By": "stefana-UploadSet"
    }, 
    "sn2011ht_20120416_sn2011ht_red11.23.txt": {
        "Type": "SN IIn", 
        "Redshift": "0.0036", 
        "Obs. Date": "2012-04-16", 
        "Program": "", 
        "Contributor": "Humphreys et al. 2012", 
        "Bibcode": "2012ApJ...760...93H", 
        "Instrument": "LBT - MODS1", 
        "Observer": "R. Stoll, K. Stanek", 
        "Reduction Status": "final", 
        "Last Modified": "2013-08-08", 
        "Modified By": "stefana-UploadSet"
    }, 
    "sn2011ht_20120416_sn2011ht_red1226.txt": {
        "Type": "SN IIn", 
        "Redshift": "0.0036", 
        "Obs. Date": "2012-04-16", 
        "Program": "", 
        "Contributor": "Humphreys et al. 2012", 
        "Bibcode": "2012ApJ...760...93H", 
        "Instrument": "LBT - MODS1", 
        "Observer": "R. Green, W. Bian, F. Bian", 
        "Reduction Status": "final", 
        "Last Modified": "2013-08-08", 
        "Modified By": "stefana-UploadSet"
    }, 
    "sn2011ht_20120416_sn2011ht_red1228.txt": {
        "Type": "SN IIn", 
        "Redshift": "0.0036", 
        "Obs. Date": "2012-04-16", 
        "Program": "", 
        "Contributor": "Humphreys et al. 2012", 
        "Bibcode": "2012ApJ...760...93H", 
        "Instrument": "LBT - MODS1", 
        "Observer": "B. Shappee, E. Ryan, R. Green, W. Bian", 
        "Reduction Status": "final", 
        "Last Modified": "2013-08-08", 
        "Modified By": "stefana-UploadSet"
    }, 
    "sn2011ht_20120417_sn2011ht_blue11.17.txt": {
        "Type": "SN IIn", 
        "Redshift": "0.0036", 
        "Obs. Date": "2012-04-17", 
        "Program": "", 
        "Contributor": "Humphreys et al. 2012", 
        "Bibcode": "2012ApJ...760...93H", 
        "Instrument": "LBT - MODS1", 
        "Observer": "R. Stoll, K. Stanek", 
        "Reduction Status": "final", 
        "Last Modified": "2013-08-08", 
        "Modified By": "stefana-UploadSet"
    }
}