{
    "PSNJ07285387p3349106_20150217_Ekar182_AFOSC_cal.ascii": {
        "Type": "SN Ibn",
        "Redshift": "0.01379",
        "Obs. Date": "2015-02-17",
        "Program": "",
        "Contributor": "Pastorello et al. 2015",
        "Bibcode": "2015MNRAS.454.4293P",
        "Instrument": "Ekar - AFOSC",
        "Observer": "Unknown",
        "Reducer": "Unknown",
        "Reduction Status": "final",
        "Last Modified": "2015-11-17",
        "Modified By": "ilanm"
    },
    "PSNJ07285387p3349106_20150218_Ekar182_AFOSC_cal.ascii": {
        "Type": "SN Ibn",
        "Redshift": "0.01379",
        "Obs. Date": "2015-02-18",
        "Program": "",
        "Contributor": "Pastorello et al. 2015",
        "Bibcode": "2015MNRAS.454.4293P",
        "Instrument": "Ekar - AFOSC",
        "Observer": "Unknown",
        "Reducer": "Unknown",
        "Reduction Status": "final",
        "Last Modified": "2015-11-17",
        "Modified By": "ilanm"
    },
    "PSNJ07285387p3349106_20150219_Ekar182_AFOSC_cal.ascii": {
        "Type": "SN Ibn",
        "Redshift": "0.01379",
        "Obs. Date": "2015-02-19",
        "Program": "",
        "Contributor": "Pastorello et al. 2015",
        "Bibcode": "2015MNRAS.454.4293P",
        "Instrument": "Ekar - AFOSC",
        "Observer": "Unknown",
        "Reducer": "Unknown",
        "Reduction Status": "final",
        "Last Modified": "2015-11-17",
        "Modified By": "ilanm"
    },
    "PSNJ07285387p3349106_20150222_NOT_ALFOSC_cal.ascii": {
        "Type": "SN Ibn",
        "Redshift": "0.01379",
        "Obs. Date": "2015-02-22",
        "Program": "",
        "Contributor": "Pastorello et al. 2015",
        "Bibcode": "2015MNRAS.454.4293P",
        "Instrument": "NOT - ALFOSC",
        "Observer": "Unknown",
        "Reducer": "Unknown",
        "Reduction Status": "final",
        "Last Modified": "2015-11-17",
        "Modified By": "ilanm"
    },
    "PSNJ07285387p3349106_20150223_TNG_LRS_cal.ascii": {
        "Type": "SN Ibn",
        "Redshift": "0.01379",
        "Obs. Date": "2015-02-23",
        "Program": "",
        "Contributor": "Pastorello et al. 2015",
        "Bibcode": "2015MNRAS.454.4293P",
        "Instrument": "TNG - DOLORES",
        "Observer": "Unknown",
        "Reducer": "Unknown",
        "Reduction Status": "final",
        "Last Modified": "2015-11-17",
        "Modified By": "ilanm"
    },
    "PSNJ07285387p3349106_20150225_TNG_LRS_cal.ascii": {
        "Type": "SN Ibn",
        "Redshift": "0.01379",
        "Obs. Date": "2015-02-25",
        "Program": "",
        "Contributor": "Pastorello et al. 2015",
        "Bibcode": "2015MNRAS.454.4293P",
        "Instrument": "TNG - DOLORES",
        "Observer": "Unknown",
        "Reducer": "Unknown",
        "Reduction Status": "final",
        "Last Modified": "2015-11-17",
        "Modified By": "ilanm"
    },
    "PSNJ07285387p3349106_20150228_TNG_LRS_cal.ascii": {
        "Type": "SN Ibn",
        "Redshift": "0.01379",
        "Obs. Date": "2015-02-28",
        "Program": "",
        "Contributor": "Pastorello et al. 2015",
        "Bibcode": "2015MNRAS.454.4293P",
        "Instrument": "TNG - DOLORES",
        "Observer": "Unknown",
        "Reducer": "Unknown",
        "Reduction Status": "final",
        "Last Modified": "2015-11-17",
        "Modified By": "ilanm"
    },
    "PSNJ07285387p3349106_20150303_NOT_ALFOSC_cal.ascii": {
        "Type": "SN Ibn",
        "Redshift": "0.01379",
        "Obs. Date": "2015-03-03",
        "Program": "",
        "Contributor": "Pastorello et al. 2015",
        "Bibcode": "2015MNRAS.454.4293P",
        "Instrument": "NOT - ALFOSC",
        "Observer": "Unknown",
        "Reducer": "Unknown",
        "Reduction Status": "final",
        "Last Modified": "2015-11-17",
        "Modified By": "ilanm"
    },
    "PSNJ07285387p3349106_20150311_NOT_ALFOSC_cal.ascii": {
        "Type": "SN Ibn",
        "Redshift": "0.01379",
        "Obs. Date": "2015-03-11",
        "Program": "",
        "Contributor": "Pastorello et al. 2015",
        "Bibcode": "2015MNRAS.454.4293P",
        "Instrument": "NOT - ALFOSC",
        "Observer": "Unknown",
        "Reducer": "Unknown",
        "Reduction Status": "final",
        "Last Modified": "2015-11-17",
        "Modified By": "ilanm"
    },
    "Private Spectra": "0"
}