{
    "SN2003dh_Apr04.dat": {
        "Type": "SN Ic-pec", 
        "Redshift": "0.1685", 
        "Obs. Date": "2003-04-04", 
        "Program": "", 
        "Contributor": "Matheson et al. 2003", 
        "Bibcode": "2003ApJ...599..394M", 
        "Instrument": "MMT - MMT-Blue", 
        "Observer": "Unknown", 
        "Reduction Status": "final", 
        "Last Modified": "2015-10-18", 
        "Modified By": "ilanm-UploadSet"
    }, 
    "SN2003dh_Apr05.dat": {
        "Type": "SN Ic-pec", 
        "Redshift": "0.1685", 
        "Obs. Date": "2003-04-05", 
        "Program": "", 
        "Contributor": "Matheson et al. 2003", 
        "Bibcode": "2003ApJ...599..394M", 
        "Instrument": "MMT - MMT-Blue", 
        "Observer": "Unknown", 
        "Reduction Status": "final", 
        "Last Modified": "2015-10-18", 
        "Modified By": "ilanm-UploadSet"
    }, 
    "SN2003dh_Apr06.dat": {
        "Type": "SN Ic-pec", 
        "Redshift": "0.1685", 
        "Obs. Date": "2003-04-06", 
        "Program": "", 
        "Contributor": "Matheson et al. 2003", 
        "Bibcode": "2003ApJ...599..394M", 
        "Instrument": "MMT - MMT-Blue", 
        "Observer": "Unknown", 
        "Reduction Status": "final", 
        "Last Modified": "2015-10-18", 
        "Modified By": "ilanm-UploadSet"
    }, 
    "SN2003dh_Apr07.dat": {
        "Type": "SN Ic-pec", 
        "Redshift": "0.1685", 
        "Obs. Date": "2003-04-07", 
        "Program": "", 
        "Contributor": "Matheson et al. 2003", 
        "Bibcode": "2003ApJ...599..394M", 
        "Instrument": "MMT - MMT-Blue", 
        "Observer": "Unknown", 
        "Reduction Status": "final", 
        "Last Modified": "2015-10-18", 
        "Modified By": "ilanm-UploadSet"
    }, 
    "SN2003dh_Apr08.dat": {
        "Type": "SN Ic-pec", 
        "Redshift": "0.1685", 
        "Obs. Date": "2003-04-08", 
        "Program": "", 
        "Contributor": "Matheson et al. 2003", 
        "Bibcode": "2003ApJ...599..394M", 
        "Instrument": "MMT - MMT-Blue", 
        "Observer": "Unknown", 
        "Reduction Status": "final", 
        "Last Modified": "2015-10-18", 
        "Modified By": "ilanm-UploadSet"
    }, 
    "SN2003dh_Apr09.dat": {
        "Type": "SN Ic-pec", 
        "Redshift": "0.1685", 
        "Obs. Date": "2003-04-09", 
        "Program": "", 
        "Contributor": "Matheson et al. 2003", 
        "Bibcode": "2003ApJ...599..394M", 
        "Instrument": "MMT - MMT-Blue", 
        "Observer": "Unknown", 
        "Reduction Status": "final", 
        "Last Modified": "2015-10-18", 
        "Modified By": "ilanm-UploadSet"
    }, 
    "SN2003dh_Apr10.dat": {
        "Type": "SN Ic-pec", 
        "Redshift": "0.1685", 
        "Obs. Date": "2003-04-10", 
        "Program": "", 
        "Contributor": "Matheson et al. 2003", 
        "Bibcode": "2003ApJ...599..394M", 
        "Instrument": "MMT - MMT-Blue", 
        "Observer": "Unknown", 
        "Reduction Status": "final", 
        "Last Modified": "2015-10-18", 
        "Modified By": "ilanm-UploadSet"
    }, 
    "SN2003dh_Apr24.dat": {
        "Type": "SN Ic-pec", 
        "Redshift": "0.1685", 
        "Obs. Date": "2003-04-24", 
        "Program": "", 
        "Contributor": "Matheson et al. 2003", 
        "Bibcode": "2003ApJ...599..394M", 
        "Instrument": "MMT - MMT-Blue", 
        "Observer": "Unknown", 
        "Reduction Status": "final", 
        "Last Modified": "2015-10-18", 
        "Modified By": "ilanm-UploadSet"
    }, 
    "SN2003dh_May02.dat": {
        "Type": "SN Ic-pec", 
        "Redshift": "0.1685", 
        "Obs. Date": "2003-05-02", 
        "Program": "", 
        "Contributor": "Matheson et al. 2003", 
        "Bibcode": "2003ApJ...599..394M", 
        "Instrument": "Magellan-Baade - Boller & Chivens", 
        "Observer": "Unknown", 
        "Reduction Status": "final", 
        "Last Modified": "2015-10-18", 
        "Modified By": "ilanm-UploadSet"
    }, 
    "SN2003dh_May04.dat": {
        "Type": "SN Ic-pec", 
        "Redshift": "0.1685", 
        "Obs. Date": "2003-05-04", 
        "Program": "", 
        "Contributor": "Matheson et al. 2003", 
        "Bibcode": "2003ApJ...599..394M", 
        "Instrument": "Magellan-Baade - Boller & Chivens", 
        "Observer": "Unknown", 
        "Reduction Status": "final", 
        "Last Modified": "2015-10-18", 
        "Modified By": "ilanm-UploadSet"
    }, 
    "SN2003dh_May0809.dat": {
        "Type": "SN Ic-pec", 
        "Redshift": "0.1685", 
        "Obs. Date": "2003-05-08", 
        "Program": "", 
        "Contributor": "Kosugi et al. 2004", 
        "Bibcode": "2004PASJ...56...61K", 
        "Instrument": "Subaru - FOCAS", 
        "Observer": "Unknown", 
        "Reduction Status": "final", 
        "Last Modified": "2015-10-18", 
        "Modified By": "ilanm-UploadSet"
    }, 
    "SN2003dh_May24.dat": {
        "Type": "SN Ic-pec", 
        "Redshift": "0.1685", 
        "Obs. Date": "2003-05-24", 
        "Program": "", 
        "Contributor": "Matheson et al. 2003", 
        "Bibcode": "2003ApJ...599..394M", 
        "Instrument": "Keck1 - LRIS", 
        "Observer": "Unknown", 
        "Reduction Status": "final", 
        "Last Modified": "2015-10-18", 
        "Modified By": "ilanm-UploadSet"
    }, 
    "SN2003dh_Jun22.dat": {
        "Type": "SN Ic-pec", 
        "Redshift": "0.1685", 
        "Obs. Date": "2003-06-22", 
        "Program": "", 
        "Contributor": "Kosugi et al. 2004", 
        "Bibcode": "2004PASJ...56...61K", 
        "Instrument": "Subaru - FOCAS", 
        "Observer": "Unknown", 
        "Reduction Status": "final", 
        "Last Modified": "2015-10-18", 
        "Modified By": "ilanm-UploadSet"
    }
}